setup.cfg
setup.py
hexs/__init__.py
hexs/hexs.py
hexs.egg-info/PKG-INFO
hexs.egg-info/SOURCES.txt
hexs.egg-info/dependency_links.txt
hexs.egg-info/top_level.txt
hexs/tests/__init__.py
hexs/tests/test_hex.py