Metadata-Version: 1.1
Name: hexs
Version: 1.1.0
Summary: Hex string formatting.
Home-page: https://github.com/kefkius/hexs
Author: Tyler Willis
Author-email: kefkius@mail.com
License: UNKNOWN
Keywords: hex,formatting
Platform: UNKNOWN
Classifier: License :: OSI Approved :: MIT License
